[{"id": "NP_579969.1", "name": "Unknown"}, {"id": "NP_619758.1", "name": "Unknown"}, {"id": "YP_006491249.1", "name": "Unknown"}, {"id": "YP_009020571.1", "name": "Unknown"}, {"id": "YP_009020585.1", "name": "Unknown"}, {"id": "YP_009051836.1", "name": "Unknown"}, {"id": "YP_009051837.1", "name": "Unknown"}, {"id": "YP_009051838.1", "name": "Unknown"}, {"id": "YP_009091825.1", "name": "Unknown"}, {"id": "YP_009091826.1", "name": "Unknown"}, {"id": "YP_009091828.1", "name": "Unknown"}, {"id": "YP_009091829.1", "name": "Unknown"}, {"id": "YP_009091830.1", "name": "Unknown"}, {"id": "YP_009094425.1", "name": "Unknown"}, {"id": "YP_009094426.1", "name": "Unknown"}, {"id": "YP_009094428.1", "name": "Unknown"}, {"id": "YP_009094429.1", "name": "Unknown"}, {"id": "YP_009094430.1", "name": "Unknown"}, {"id": "YP_009094431.1", "name": "Unknown"}, {"id": "YP_009094432.1", "name": "Unknown"}, {"id": "YP_009094433.1", "name": "Unknown"}, {"id": "YP_009094434.1", "name": "Unknown"}, {"id": "YP_009117083.1", "name": "Unknown"}, {"id": "YP_009117084.1", "name": "Unknown"}, {"id": "YP_009117085.1", "name": "Unknown"}, {"id": "YP_009164031.1", "name": "Unknown"}, {"id": "YP_009259274.1", "name": "Unknown"}, {"id": "YP_009345031.1", "name": "Unknown"}, {"id": "YP_009346010.1", "name": "Unknown"}, {"id": "YP_009346011.1", "name": "Unknown"}, {"id": "YP_009346012.1", "name": "Unknown"}, {"id": "YP_009346034.1", "name": "Unknown"}, {"id": "YP_009362071.1", "name": "Unknown"}, {"id": "YP_009362072.1", "name": "Unknown"}, {"id": "YP_009362073.1", "name": "Unknown"}, {"id": "YP_009362079.1", "name": "Unknown"}, {"id": "YP_009512965.1", "name": "Unknown"}, {"id": "YP_009512966.1", "name": "Unknown"}, {"id": "YP_009512967.1", "name": "Unknown"}, {"id": "YP_009512968.1", "name": "Unknown"}, {"id": "YP_009512969.1", "name": "Unknown"}, {"id": "YP_009512970.1", "name": "Unknown"}, {"id": "YP_009512971.1", "name": "Unknown"}, {"id": "YP_009666331.1", "name": "Unknown"}, {"id": "YP_009666332.1", "name": "Unknown"}, {"id": "YP_009666333.1", "name": "Unknown"}, {"id": "YP_009666334.1", "name": "Unknown"}, {"id": "YP_009666970.1", "name": "Unknown"}, {"id": "YP_009666971.1", "name": "Unknown"}, {"id": "YP_009666972.1", "name": "Unknown"}, {"id": "YP_010085064.1", "name": "Unknown"}, {"id": "YP_010085065.1", "name": "Unknown"}, {"id": "YP_010085066.1", "name": "Unknown"}, {"id": "YP_010086121.1", "name": "Unknown"}, {"id": "YP_010086122.1", "name": "Unknown"}, {"id": "YP_010086123.1", "name": "Unknown"}, {"id": "YP_010086124.1", "name": "Unknown"}, {"id": "YP_010805751.1", "name": "Unknown"}, {"id": "YP_010805752.1", "name": "Unknown"}, {"id": "YP_010805753.1", "name": "Unknown"}, {"id": "YP_010805754.1", "name": "Unknown"}, {"id": "YP_010805755.1", "name": "Unknown"}, {"id": "YP_010805756.1", "name": "Unknown"}, {"id": "YP_010805757.1", "name": "Unknown"}]